{"idle": {"end_frame": 12, "property_list": ["xspeed", "yspeed"], "properties": {"xspeed": [[0, 0, 12]], "yspeed": [[0, 0, 12]]}, "cancel_list": [[["down"], [[0, 12]], "crouch"], [["smdir"], [[0, 12]], "dash"], [["opdir"], [[0, 12]], "dash"], [["mod2"], [[0, 12]], "shield"]], "flip": 0, "default_link": "idle"}
,"downtilt": {"end_frame": 6, "property_list": ["xspeed","yspeed"], "properties": {"xspeed": [[0, 0, 6]], "yspeed": [[0, 0, 6]]}, "cancel_list": [], "flip": 0, "default_link": "idle"}
,"crouch": {"end_frame": 0, "property_list": ["xspeed","yspeed"], "properties": {"xspeed": [[0, 0, 1]], "yspeed": [[0, 0, 1]]}, "cancel_list": [[["mod1"], [[0, 1]], "downtilt"], [["down"], [[0, 1]], "crouch"]], "flip": 0, "default_link": "idle"}
,"dash": {"end_frame": 5, "property_list": ["xspeed","yspeed"], "properties": {"xspeed": [[5, 0, 5]], "yspeed": [[0, 0, 5]]}, "cancel_list": [[["smdir"], [[5, 5]], "run"]], "flip": 1, "default_link": "idle"}
,"run": {"end_frame": 0, "property_list": ["xspeed","yspeed"], "properties": {"xspeed": [[9, 0, 1]], "yspeed": [[0, 0, 1]]}, "cancel_list": [[["smdir"], [[0, 1]], "run"]], "flip": 0, "default_link": "idle"} 
,"freefall": {"end_frame": 12, "property_list": [], "properties": {}, "cancel_list": [[["isfloor"], [[0, 12]], "idle"]], "flip": 0, "default_link": "freefall"}
, "js": {"end_frame": 3, "property_list": ["yspeed","isplat", "isground"], "properties": {"yspeed": [[0, 0, 2], [24,3,3]], "isplat": [[false, 3,3]], "isground": [[false, 3,3]]}, "cancel_list": [], "flip": 0, "default_link": "freefall"}
,"shield": {"end_frame": 0, "property_list": [], "properties": {}, "cancel_list": [[["empty_shield"], [[0, 1]], "shield_break"], [["mod2"], [[0, 1]], "shield"]], "flip": 0, "default_link": "idle"}
,"shield_break": {"end_frame": 50, "property_list": ["empty_shield", "shield"], "properties": {"empty_shield" : [[false, 50,50]], "shield" : [[30,50,50]]}, "cancel_list": [], "flip": 0, "default_link": "idle"}}

